getmwmap/__init__.py
getmwmap-1.0.2.dist-info/LICENSE
getmwmap-1.0.2.dist-info/METADATA
getmwmap-1.0.2.dist-info/WHEEL
getmwmap-1.0.2.dist-info/top_level.txt
getmwmap-1.0.2.dist-info/RECORD
