Metadata-Version: 2.1
Name: getmwmap
Version: 1.0.2
Summary: 为MW锦标赛提高快速随机抽取地图的拓展
Home-page: https://github.com/KindLittleTurtle/getmwmap
Author: MWCTTO
Author-email: to@mwtour.cn
License: AGPL3.0
Platform: UNKNOWN
License-File: LICENSE
